pycomfy/__init__.py
pycomfy/client.py
pycomfy/exceptions.py
pycomfy/utils.py
pycomfy/workflow.py
pycomfy/templates/__init__.py
pycomfy/templates/default_text_to_image.json
pycomfy-0.4.0.dist-info/licenses/LICENSE
pycomfy-0.4.0.dist-info/METADATA
pycomfy-0.4.0.dist-info/WHEEL
pycomfy-0.4.0.dist-info/top_level.txt
pycomfy-0.4.0.dist-info/RECORD
