Metadata-Version: 2.4
Name: pycomfy
Version: 0.4.0
Summary: A simple and robust Python client library for the ComfyUI API.
Author: JusteLeo
License-Expression: MIT
Project-URL: Homepage, https://github.com/votre_nom/pycomfy
Project-URL: Issues, https://github.com/votre_nom/pycomfy/issues
Classifier: Programming Language :: Python :: 3
Classifier: Operating System :: OS Independent
Classifier: Topic :: Scientific/Engineering :: Artificial Intelligence
Requires-Python: >=3.8
License-File: LICENSE
Requires-Dist: requests
Requires-Dist: websocket-client
Requires-Dist: Pillow
Requires-Dist: huggingface-hub
Dynamic: license-file
